<?xml version="1.0" encoding="utf-8" ?>
<dwsync>
<file name="naradi_draty.jpg" server="79175.w75.wedos.net" local="130990071739052008" remote="130990095600000000" Dst="1" />
<file name="naradi_bity.jpg" server="79175.w75.wedos.net" local="130990115832321348" remote="130990095600000000" Dst="1" />
<file name="naradi_brousky.jpg" server="79175.w75.wedos.net" local="130990072385391294" remote="130990095600000000" Dst="1" />
<file name="naradi_kladivo.jpg" server="79175.w75.wedos.net" local="130990070872840777" remote="130990095600000000" Dst="1" />
<file name="naradi_hrebiky_300x70.jpg" server="79175.w75.wedos.net" local="130990072537037535" remote="130990095600000000" Dst="1" />
<file name="naradi_kleste.jpg" server="79175.w75.wedos.net" local="130990071678017202" remote="130990096200000000" Dst="1" />
<file name="naradi_klice.jpg" server="79175.w75.wedos.net" local="130990071806676139" remote="130990096200000000" Dst="1" />
<file name="naradi_libela.jpg" server="79175.w75.wedos.net" local="130990129255151716" remote="130990096200000000" Dst="1" />
<file name="naradi_metry.jpg" server="79175.w75.wedos.net" local="130990072448262768" remote="130990096200000000" Dst="1" />
<file name="naradi_nuz.jpg" server="79175.w75.wedos.net" local="130990070809896289" remote="130990096200000000" Dst="1" />
<file name="naradi_napln_konik.jpg" server="79175.w75.wedos.net" local="130990070955629174" remote="130990096200000000" Dst="1" />
<file name="naradi_odlamovaci_nuz_napln.jpg" server="79175.w75.wedos.net" local="130990071361700429" remote="130990096200000000" Dst="1" />
<file name="naradi_pantok.jpg" server="79175.w75.wedos.net" local="130990071302763977" remote="130990096200000000" Dst="1" />
<file name="naradi_pila1.jpg" server="79175.w75.wedos.net" local="130990072009422874" remote="130990096800000000" Dst="1" />
<file name="naradi_pila3.jpg" server="79175.w75.wedos.net" local="130990127565204909" remote="130990096800000000" Dst="1" />
<file name="naradi_pila2.jpg" server="79175.w75.wedos.net" local="130990071617701768" remote="130990096800000000" Dst="1" />
<file name="naradi_pilniky_dlata_spachtla.jpg" server="79175.w75.wedos.net" local="130990071429382036" remote="130990096800000000" Dst="1" />
<file name="naradi_racna.jpg" server="79175.w75.wedos.net" local="130990071221947124" remote="130990096800000000" Dst="1" />
<file name="naradi_sekera.jpg" server="79175.w75.wedos.net" local="130990072323748768" remote="130990096800000000" Dst="1" />
<file name="naradi_rysovacky.jpg" server="79175.w75.wedos.net" local="130990071490014503" remote="130990096800000000" Dst="1" />
<file name="naradi_vrtaky.jpg" server="79175.w75.wedos.net" local="130990115782559627" remote="130990096800000000" Dst="1" />
<file name="naradi_sekera_bez_topora.jpg" server="79175.w75.wedos.net" local="130990072204821669" remote="130990096800000000" Dst="1" />
<file name="naradi_stipacky.jpg" server="79175.w75.wedos.net" local="130990072263028010" remote="130990096800000000" Dst="1" />
<file name="naradi_vrtaky2.jpg" server="79175.w75.wedos.net" local="130990128932761738" remote="130990097400000000" Dst="1" />
<file name="naradi_vruty_150.jpg" server="79175.w75.wedos.net" local="130990072145220282" remote="130990097400000000" Dst="1" />
<file name="naradi_oka_a_haky.jpg" server="79175.w75.wedos.net" local="130990121457652707" remote="130990097400000000" Dst="1" />
<file name="naradi_vzorovnik.jpg" server="79175.w75.wedos.net" local="130990129957577332" remote="130990098000000000" Dst="1" />
<file name="naradi_vruty_50x50.jpg" server="79175.w75.wedos.net" local="130990071945832821" remote="130990098000000000" Dst="1" />
<file name="naradi_konik.jpg" server="79175.w75.wedos.net" local="130990072073600352" remote="130990099200000000" Dst="1" />
</dwsync>